jlab_create_sas_file/__init__.py
jlab_create_sas_file/_version.py
jlab_create_sas_file/labextension/build_log.json
jlab_create_sas_file/labextension/package.json
jlab_create_sas_file/labextension/static/lib_index_js.daadba9315563ecc1566.js
jlab_create_sas_file/labextension/static/lib_index_js.daadba9315563ecc1566.js.map
jlab_create_sas_file/labextension/static/remoteEntry.9012dff7540167185f75.js
jlab_create_sas_file/labextension/static/remoteEntry.9012dff7540167185f75.js.map
jlab_create_sas_file/labextension/static/style.js
jlab_create_sas_file/labextension/static/style_index_js.7a3a6683411a99318050.js
jlab_create_sas_file/labextension/static/style_index_js.7a3a6683411a99318050.js.map
jlab_create_sas_file/labextension/static/vendors-node_modules_css-loader_dist_runtime_api_js-node_modules_css-loader_dist_runtime_cssW-926fd9.02f9c2f7b731cd679388.js
jlab_create_sas_file/labextension/static/vendors-node_modules_css-loader_dist_runtime_api_js-node_modules_css-loader_dist_runtime_cssW-926fd9.02f9c2f7b731cd679388.js.map
jlab_create_sas_file-0.1.0.data/data/share/jupyter/labextensions/jlab-create-sas-file/build_log.json
jlab_create_sas_file-0.1.0.data/data/share/jupyter/labextensions/jlab-create-sas-file/install.json
jlab_create_sas_file-0.1.0.data/data/share/jupyter/labextensions/jlab-create-sas-file/package.json
jlab_create_sas_file-0.1.0.data/data/share/jupyter/labextensions/jlab-create-sas-file/static/lib_index_js.daadba9315563ecc1566.js
jlab_create_sas_file-0.1.0.data/data/share/jupyter/labextensions/jlab-create-sas-file/static/lib_index_js.daadba9315563ecc1566.js.map
jlab_create_sas_file-0.1.0.data/data/share/jupyter/labextensions/jlab-create-sas-file/static/remoteEntry.9012dff7540167185f75.js
jlab_create_sas_file-0.1.0.data/data/share/jupyter/labextensions/jlab-create-sas-file/static/remoteEntry.9012dff7540167185f75.js.map
jlab_create_sas_file-0.1.0.data/data/share/jupyter/labextensions/jlab-create-sas-file/static/style.js
jlab_create_sas_file-0.1.0.dist-info/LICENSE
jlab_create_sas_file-0.1.0.dist-info/METADATA
jlab_create_sas_file-0.1.0.dist-info/WHEEL
jlab_create_sas_file-0.1.0.dist-info/top_level.txt
jlab_create_sas_file-0.1.0.dist-info/RECORD
